xpressinsight/__init__.py
xpressinsight/app_base.py
xpressinsight/app_runner.py
xpressinsight/code_generator.py
xpressinsight/entities_config.py
xpressinsight/exec_mode.py
xpressinsight/exec_resource_group.py
xpressinsight/mosel.py
xpressinsight/mosel_keywords.py
xpressinsight/polars_shims.py
xpressinsight/repository_path.py
xpressinsight/slow_tasks_monitor.py
xpressinsight/test_runner.py
xpressinsight/type_checking.py
xpressinsight/data/__init__.py
xpressinsight/data/helpers.py
xpressinsight/data_connectors/__init__.py
xpressinsight/data_connectors/app_data_connector.py
xpressinsight/data_connectors/data_connector.py
xpressinsight/data_connectors/insight_worker_parquet_connector.py
xpressinsight/data_connectors/parquet_connector.py
xpressinsight/data_connectors/rest_api_connector.py
xpressinsight/data_connectors/table_connector.py
xpressinsight/entities/__init__.py
xpressinsight/entities/basic_types.py
xpressinsight/entities/data_frame.py
xpressinsight/entities/entity.py
xpressinsight/entities/index.py
xpressinsight/entities/scalar.py
xpressinsight/entities/series.py
xpressinsight/entities/utils.py
xpressinsight/interface/__init__.py
xpressinsight/interface/attach_errors.py
xpressinsight/interface/interface.py
xpressinsight/interface/interface_base.py
xpressinsight/interface/interface_errors.py
xpressinsight/interface/interface_rest.py
xpressinsight/interface/interface_test.py
xpressinsight/interface/apprunner_rest_client/__init__.py
xpressinsight/interface/apprunner_rest_client/api_client.py
xpressinsight/interface/apprunner_rest_client/configuration.py
xpressinsight/interface/apprunner_rest_client/exceptions.py
xpressinsight/interface/apprunner_rest_client/rest.py
xpressinsight/interface/apprunner_rest_client/api/__init__.py
xpressinsight/interface/apprunner_rest_client/api/default_api.py
xpressinsight/interface/apprunner_rest_client/models/__init__.py
xpressinsight/interface/apprunner_rest_client/models/attach_status.py
xpressinsight-1.15.0.dist-info/LICENSE.txt
xpressinsight-1.15.0.dist-info/METADATA
xpressinsight-1.15.0.dist-info/WHEEL
xpressinsight-1.15.0.dist-info/top_level.txt
xpressinsight-1.15.0.dist-info/RECORD
