Metadata-Version: 2.1
Name: xpressinsight
Version: 1.15.0
Summary: FICO Xpress - Insight Python package
Author-email: "FICO Xpress dev. team" <support@fico.com>
License: Shrinkwrap License Agreement
Project-URL: Homepage, https://www.fico.com/en/products/fico-xpress-optimization
Project-URL: Documentation, https://www.fico.com/fico-xpress-optimization/docs/latest/insight-python-doc/xi-introduction.html
Keywords: optimization,xpress,insight
Classifier: License :: Other/Proprietary License
Classifier: Development Status :: 5 - Production/Stable
Classifier: Intended Audience :: Science/Research
Classifier: Intended Audience :: Developers
Classifier: Programming Language :: Python
Classifier: Programming Language :: Python :: 3
Classifier: Programming Language :: Python :: 3.9
Classifier: Programming Language :: Python :: 3.10
Classifier: Programming Language :: Python :: 3.11
Classifier: Programming Language :: Python :: 3.12
Classifier: Programming Language :: Python :: 3.13
Classifier: Topic :: Software Development
Classifier: Topic :: Scientific/Engineering
Classifier: Operating System :: OS Independent
Requires-Python: >=3.9
License-File: LICENSE.txt
Requires-Dist: pyarrow>=4.0.0
Requires-Dist: pandas>=1.0.0
Requires-Dist: numpy>=1.17.0
Requires-Dist: urllib3
Requires-Dist: certifi
Requires-Dist: python-dateutil>=2.8.2
Requires-Dist: pydantic>=2.5.3
Requires-Dist: packaging>=23.0
Requires-Dist: requests<3,>=2.28.0
Requires-Dist: requests-toolbelt<2,>=1.0.0
Requires-Dist: keyring>=24.3.0
Requires-Dist: deprecated>=1.2.0
Requires-Dist: typing-extensions>=4.6.0; python_version < "3.12.0"
